setup.py
api_star/__init__.py
api_star/authentication.py
api_star/compat.py
api_star/core.py
api_star/decorators.py
api_star/environment.py
api_star/exceptions.py
api_star/parsers.py
api_star/permissions.py
api_star/renderers.py
api_star/request.py
api_star/schema.py
api_star/test.py
api_star/utils.py
api_star/validators.py
api_star.egg-info/PKG-INFO
api_star.egg-info/SOURCES.txt
api_star.egg-info/dependency_links.txt
api_star.egg-info/requires.txt
api_star.egg-info/top_level.txt
api_star/__pycache__/__init__.cpython-33.pyc
api_star/__pycache__/__init__.cpython-34.pyc
api_star/__pycache__/authentication.cpython-33.pyc
api_star/__pycache__/authentication.cpython-34.pyc
api_star/__pycache__/compat.cpython-33.pyc
api_star/__pycache__/compat.cpython-34.pyc
api_star/__pycache__/core.cpython-33.pyc
api_star/__pycache__/core.cpython-34.pyc
api_star/__pycache__/decorators.cpython-33.pyc
api_star/__pycache__/decorators.cpython-34.pyc
api_star/__pycache__/environment.cpython-33.pyc
api_star/__pycache__/environment.cpython-34.pyc
api_star/__pycache__/exceptions.cpython-33.pyc
api_star/__pycache__/exceptions.cpython-34.pyc
api_star/__pycache__/links.cpython-34.pyc
api_star/__pycache__/parsers.cpython-33.pyc
api_star/__pycache__/parsers.cpython-34.pyc
api_star/__pycache__/permissions.cpython-33.pyc
api_star/__pycache__/permissions.cpython-34.pyc
api_star/__pycache__/renderers.cpython-33.pyc
api_star/__pycache__/renderers.cpython-34.pyc
api_star/__pycache__/request.cpython-33.pyc
api_star/__pycache__/request.cpython-34.pyc
api_star/__pycache__/schema.cpython-33.pyc
api_star/__pycache__/schema.cpython-34.pyc
api_star/__pycache__/test.cpython-33.pyc
api_star/__pycache__/test.cpython-34.pyc
api_star/__pycache__/utils.cpython-33.pyc
api_star/__pycache__/utils.cpython-34.pyc
api_star/__pycache__/validators.cpython-33.pyc
api_star/__pycache__/validators.cpython-34.pyc
api_star/frameworks/__init__.py
api_star/frameworks/__pycache__/__init__.cpython-33.pyc
api_star/frameworks/__pycache__/__init__.cpython-34.pyc
api_star/frameworks/django/__init__.py
api_star/frameworks/django/app.py
api_star/frameworks/django/urls.py
